{
  "id": "s15-silvia-drifting",
  "title": "Drifting Nissan Silvia S15 Coloring Page",
  "category": "Vehicles & Transport",
  "subcategory": "Cars",
  "tags": [
    "car",
    "nissan",
    "silvia",
    "s15",
    "drifting",
    "vehicle"
  ],
  "seoTitle": "Medium Drifting Nissan Silvia S15 Coloring Page - Free PDF | ColoringPalace",
  "seoDescription": "Download and print this medium drifting Nissan Silvia S15 coloring sheet. High-resolution free printable PDF showing a Japanese sports coupe drifting around a mountain curve.",
  "difficulty": "Medium",
  "author": "Antigravity Agent"
}