{
  "id": "fairy-sitting-flower",
  "title": "Fairy Sitting on Flower Coloring Page",
  "category": "Fantasy & Fairy Tales",
  "subcategory": "Fairies",
  "tags": [
    "fantasy",
    "fairy",
    "flower",
    "garden"
  ],
  "seoTitle": "Medium Fairy Sitting on Flower Coloring Page - Free PDF | ColoringPalace",
  "seoDescription": "Download and print this medium fairy sitting on flower coloring sheet. Ideal for kids and teens with balanced outlines, natural textures, and a beautiful scenic background. Free printable PDF.",
  "difficulty": "Medium",
  "author": "Antigravity Agent",
  "funFacts": [
    "Many legends depict mythical beasts as guardians of nature, ancient treasures, and enchanted realms.",
    "Phoenixes and other mythical creatures represent themes of rebirth, fire, and magical transformation."
  ]
}