{
  "id": "cute-magical-mascot",
  "title": "Cute Magical Mascot Floating Coloring Page",
  "category": "Anime & Manga",
  "subcategory": "Magical Girls",
  "tags": [
    "anime",
    "magical",
    "mascot",
    "cute"
  ],
  "seoTitle": "Easy Cute Magical Mascot Floating Coloring Page - Free PDF | ColoringPalace",
  "seoDescription": "Download and print this easy cute magical mascot floating coloring sheet. Perfect for toddlers and young kids with thick outlines and large coloring spaces. High-resolution free vector PDF.",
  "difficulty": "Easy",
  "author": "Antigravity Agent",
  "funFacts": [
    "Anime stories often feature magical girls with spells and armored knights protecting fantasy kingdoms.",
    "Ninjas and sword warriors are classic figures of historical Japanese action legends."
  ]
}