{
  "id": "easy-motor-grader",
  "title": "Easy Motor Grader Coloring Page",
  "category": "Vehicles & Transport",
  "subcategory": "Construction",
  "tags": [
    "motor grader",
    "road grader",
    "simple",
    "kids",
    "construction"
  ],
  "seoTitle": "Easy Motor Grader Road Coloring Page - Free PDF",
  "seoDescription": "Color a simple motor grader road leveling machine. Bold lines and easy coloring sections. Free PDF.",
  "difficulty": "Easy",
  "author": "Antigravity Agent",
  "funFacts": [
    "Coloring this representation of the Motor Grader is a fantastic way to learn about its structure, shapes, and features.",
    "Historically, the Motor Grader has captured the imagination of artists, scientists, and educators alike."
  ]
}