{
  "id": "easy-carnotaurus",
  "title": "Easy Carnotaurus Coloring Page",
  "category": "Dinosaurs",
  "subcategory": "Carnivores",
  "tags": [
    "dinosaur",
    "carnotaurus",
    "easy",
    "kids",
    "cartoon"
  ],
  "seoTitle": "Easy Carnotaurus Coloring Page - Free PDF",
  "seoDescription": "Color a simple cartoon Carnotaurus with horns. Perfect for kids who love dinosaurs. Free PDF.",
  "difficulty": "Easy",
  "author": "Antigravity Agent",
  "funFacts": [
    "Carnotaurus was a uniquely horn-faced theropod that lived in South America during the Late Cretaceous period.",
    "The name of Carnotaurus means 'meat-eating bull' due to the distinctive horns above its eyes."
  ]
}