{
  "id": "easy-giant-squid",
  "title": "Easy Giant Squid Coloring Page",
  "category": "Ocean Life",
  "subcategory": "Cephalopods",
  "tags": [
    "giant squid",
    "squid",
    "easy",
    "kids",
    "cartoon"
  ],
  "seoTitle": "Easy Giant Squid Coloring Page - Free PDF",
  "seoDescription": "Print this simple giant squid coloring page. Ideal for preschool and kindergartners. Free PDF.",
  "difficulty": "Easy",
  "author": "Antigravity Agent",
  "funFacts": [
    "This high-quality coloring page is designed to offer a fantastic creative experience.",
    "Coloring is a scientifically proven way to increase focus, activate both brain hemispheres, and reduce daily stress.",
    "Ensure your printer scale settings are adjusted to 'Fit to Page' for a clean border alignment when printing."
  ]
}